nepal_const_doc_chunker/__init__.py
nepal_const_doc_chunker/chunking.py
nepal_const_doc_chunker/loader.py
nepal_const_doc_chunker/main.py
nepal_const_doc_chunker/utils.py
nepal_const_doc_chunker-0.4.0.dist-info/METADATA
nepal_const_doc_chunker-0.4.0.dist-info/WHEEL
nepal_const_doc_chunker-0.4.0.dist-info/top_level.txt
nepal_const_doc_chunker-0.4.0.dist-info/RECORD
