Metadata-Version: 2.1
Name: nepal_const_doc_chunker
Version: 0.4.0
Requires-Dist: loguru>=0.7.2
Requires-Dist: langchain-community>=0.2.17
Requires-Dist: PyMuPDF>=1.24.11
